watchlog_connect_py/__init__.py
watchlog_connect_py/watchlog.py
watchlog_connect_py-0.0.5.dist-info/LICENSE
watchlog_connect_py-0.0.5.dist-info/METADATA
watchlog_connect_py-0.0.5.dist-info/WHEEL
watchlog_connect_py-0.0.5.dist-info/top_level.txt
watchlog_connect_py-0.0.5.dist-info/RECORD
