Metadata-Version: 2.1
Name: watchlog-connect-py
Version: 0.0.5
Summary: This is a package for connect to watchlog and send custom metrics
Author-email: mohammadnajm <mohammadnajm75@email.com>
Project-URL: Homepage, https://github.com/mohammadnajm/watchlog-connect-py
Project-URL: Bug Tracker, https://github.com/mohammadnajm/watchlog-connect-py/issues
Classifier: Programming Language :: Python :: 3
Classifier: License :: OSI Approved :: MIT License
Classifier: Operating System :: OS Independent
Requires-Python: >=3.7
License-File: LICENSE
